{"success":true,"code":0,"msg":"成功","data":{"score":0,"isMark":0,"submitTime":1571897324000,"examTitle":"中式烹调师-初级-练习试卷","examId":"1563504780152398","examType":1,"examScore":100.00,"examNumber":-1,"UserExamAnswersVO":{"judge":[{"examQuestionId":"1571826502478789","examQuestionTitle":"在刀法的运用中，段可用直刀法与斜刀法产生，因此，在形态上，段可分为直刀段与斜刀段。","type":3,"options":"[\"正确\",\"错误\"]","userAnswer":"[]","answer":"[\"正确\"]","analysis":null,"diffculty":3,"rightOrWrong":2,"score":1.00,"userQuestionScenarios":null},{"examQuestionId":"1571826502290468","examQuestionTitle":"鸡翅剔骨的步骤应是：割断肱骨关节四周的筋膜，将翅肉翻转，再割断尺骨、桡骨上的筋膜，取下肱骨及尺骨、桡骨。翅尖部位的骨骼一般在生料剔骨时予以保留。","type":3,"options":"[\"正确\",\"错误\"]","userAnswer":"[]","answer":"[\"正确\"]","analysis":null,"diffculty":2,"rightOrWrong":2,"score":1.00,"userQuestionScenarios":null},{"examQuestionId":"1571826506430901","examQuestionTitle":"冷菜的色泽较暗淡，不够醒目的冷盘，可以不用点缀。","type":3,"options":"[\"正确\",\"错误\"]","userAnswer":"[]","answer":"[\"错误\"]","analysis":null,"diffculty":3,"rightOrWrong":2,"score":1.00,"userQuestionScenarios":null},{"examQuestionId":"1571826506390538","examQuestionTitle":"制作冷菜装盘时尽量减少原料与手直接接触的机会，提倡使用工具取拿原料。","type":3,"options":"[\"正确\",\"错误\"]","userAnswer":"[]","answer":"[\"正确\"]","analysis":null,"diffculty":3,"rightOrWrong":2,"score":1.00,"userQuestionScenarios":null},{"examQuestionId":"1571826502842864","examQuestionTitle":"主辅料组配时应遵照质价相等规律确定菜肴原料的数量。一般来说，应本着粗菜细做、细菜精做、物尽其用、避免浪费的原则，尽量降低原料成本。","type":3,"options":"[\"正确\",\"错误\"]","userAnswer":"[]","answer":"[\"正确\"]","analysis":null,"diffculty":3,"rightOrWrong":2,"score":1.00,"userQuestionScenarios":null},{"examQuestionId":"1571826501761577","examQuestionTitle":"适用微波炉的优点是对不吸收的玻璃，塑料等介质穿透性好，可使能量直达食物，如果选用适宜的频率，就可以将食物内外加热均匀。","type":3,"options":"[\"正确\",\"错误\"]","userAnswer":"[]","answer":"[\"正确\"]","analysis":null,"diffculty":2,"rightOrWrong":2,"score":1.00,"userQuestionScenarios":null},{"examQuestionId":"1571826506029670","examQuestionTitle":"锋利刀的现象是圆锋，用而不磨，膛刀过多，刀圆厚，久磨不利。","type":3,"options":"[\"正确\",\"错误\"]","userAnswer":"[]","answer":"[\"错误\"]","analysis":null,"diffculty":2,"rightOrWrong":2,"score":1.00,"userQuestionScenarios":null},{"examQuestionId":"1571826501452334","examQuestionTitle":"在预煮或烹调过程中加入各种香幸调料，利用挥发作用除去原料中的异味。","type":3,"options":"[\"正确\",\"错误\"]","userAnswer":"[]","answer":"[\"正确\"]","analysis":null,"diffculty":2,"rightOrWrong":2,"score":1.00,"userQuestionScenarios":null},{"examQuestionId":"1571826501331293","examQuestionTitle":"冷菜装盘对刀工的要求片与片或块与块之间的拼摆，间距可以不一致，不做到整齐划一。","type":3,"options":"[\"正确\",\"错误\"]","userAnswer":"[]","answer":"[\"错误\"]","analysis":null,"diffculty":2,"rightOrWrong":2,"score":1.00,"userQuestionScenarios":null},{"examQuestionId":"1571826501085772","examQuestionTitle":"切割成形后的原料不必符合进餐对象的宗教信仰和饮食习惯的要求。","type":3,"options":"[\"正确\",\"错误\"]","userAnswer":"[]","answer":"[\"错误\"]","analysis":null,"diffculty":2,"rightOrWrong":2,"score":1.00,"userQuestionScenarios":null},{"examQuestionId":"1571826504198647","examQuestionTitle":"平刀法在运刀时用力要注意平衡，不应此轻彼重，以免产生凹凸不平的现象。","type":3,"options":"[\"正确\",\"错误\"]","userAnswer":"[]","answer":"[\"正确\"]","analysis":null,"diffculty":3,"rightOrWrong":2,"score":1.00,"userQuestionScenarios":null},{"examQuestionId":"1571826500601241","examQuestionTitle":"鸭，鹅等水禽类烫泡时间可短些，烫毛水温略低；鸡，鸽子，鹌鹑家禽烫毛时间相对长一些，烫毛水温略高。","type":3,"options":"[\"正确\",\"错误\"]","userAnswer":"[]","answer":"[\"错误\"]","analysis":null,"diffculty":2,"rightOrWrong":2,"score":1.00,"userQuestionScenarios":null},{"examQuestionId":"1571826504003918","examQuestionTitle":"完全解冻状态下的原料，应立即加工、烹饪，以防止肉质和风味的改变。","type":3,"options":"[\"正确\",\"错误\"]","userAnswer":"[]","answer":"[\"正确\"]","analysis":null,"diffculty":3,"rightOrWrong":2,"score":1.00,"userQuestionScenarios":null},{"examQuestionId":"1571826506353335","examQuestionTitle":"直切刀法属于其它刀法。","type":3,"options":"[\"正确\",\"错误\"]","userAnswer":"[]","answer":"[\"错误\"]","analysis":null,"diffculty":3,"rightOrWrong":2,"score":1.00,"userQuestionScenarios":null},{"examQuestionId":"1571826503521110","examQuestionTitle":"菜肴色彩的调配，并非美术中的调色那么容易，多数需用加热的手段来完成。","type":3,"options":"[\"正确\",\"错误\"]","userAnswer":"[]","answer":"[\"正确\"]","analysis":null,"diffculty":3,"rightOrWrong":2,"score":1.00,"userQuestionScenarios":null},{"examQuestionId":"1571826506686832","examQuestionTitle":"淀粉在使用前应先浸泡在水中，使淀粉粒充分吸水膨胀，以获得较高的黏度，从而增加在烹饪原料上的黏附性。","type":3,"options":"[\"正确\",\"错误\"]","userAnswer":"[]","answer":"[\"正确\"]","analysis":null,"diffculty":3,"rightOrWrong":2,"score":1.00,"userQuestionScenarios":null},{"examQuestionId":"1571826432118713","examQuestionTitle":"等腰三角块又称正三角块，即三角块的两腰边长相等，边长不超过3cm，块面平整，常用于豆腐及豆干。","type":3,"options":"[\"正确\",\"错误\"]","userAnswer":"[]","answer":"[\"正确\"]","analysis":null,"diffculty":3,"rightOrWrong":2,"score":1.00,"userQuestionScenarios":null},{"examQuestionId":"1571826503450667","examQuestionTitle":"高压蒸汽柜是利用蒸汽喷嘴喷出高压蒸汽流，在瞬间加热食物，操作方便。","type":3,"options":"[\"正确\",\"错误\"]","userAnswer":"[]","answer":"[\"正确\"]","analysis":null,"diffculty":3,"rightOrWrong":2,"score":1.00,"userQuestionScenarios":null},{"examQuestionId":"1571826501352295","examQuestionTitle":"风味性拍粉是指拍粉工艺主要内容，拍粉后经炸制或油煎直接成菜，形成拍粉菜品独特的松香风味。","type":3,"options":"[\"正确\",\"错误\"]","userAnswer":"[]","answer":"[\"正确\"]","analysis":null,"diffculty":2,"rightOrWrong":2,"score":1.00,"userQuestionScenarios":null},{"examQuestionId":"1571826506191825","examQuestionTitle":"原料切割时，正确规范的技术动作是对原料成形质量，提高工作效率，减少职业疾病等都具有重要作用。","type":3,"options":"[\"正确\",\"错误\"]","userAnswer":"[]","answer":"[\"正确\"]","analysis":null,"diffculty":3,"rightOrWrong":2,"score":1.00,"userQuestionScenarios":null},{"examQuestionId":"1571826431754511","examQuestionTitle":"反斜刀法运刀时，左手按料，刀身倾斜抵住左手指节。","type":3,"options":"[\"正确\",\"错误\"]","userAnswer":"[]","answer":"[\"正确\"]","analysis":null,"diffculty":3,"rightOrWrong":2,"score":1.00,"userQuestionScenarios":null},{"examQuestionId":"1571826501217597","examQuestionTitle":"凡旺火速成的炒，爆烹制的菜肴，其原料形状需加工成丁，丝，条，片，茸，泥等细小的形状。","type":3,"options":"[\"正确\",\"错误\"]","userAnswer":"[]","answer":"[\"正确\"]","analysis":null,"diffculty":2,"rightOrWrong":2,"score":1.00,"userQuestionScenarios":null},{"examQuestionId":"1571826500548209","examQuestionTitle":"对于有残留农药的蔬菜不需进行反复冲洗，浸漂，彻底清除蔬菜上残留的农药。","type":3,"options":"[\"正确\",\"错误\"]","userAnswer":"[]","answer":"[\"错误\"]","analysis":null,"diffculty":3,"rightOrWrong":2,"score":1.00,"userQuestionScenarios":null},{"examQuestionId":"1571826506229594","examQuestionTitle":"握刀势是手心紧贴刀柄，小指与无名指屈起紧捏刀柄，食指、中指屈起握刀箍，拇指紧贴刀身。","type":3,"options":"[\"正确\",\"错误\"]","userAnswer":"[]","answer":"[\"正确\"]","analysis":null,"diffculty":2,"rightOrWrong":2,"score":1.00,"userQuestionScenarios":null},{"examQuestionId":"1571826432355410","examQuestionTitle":"直刀片的切面应光滑，片形均匀，厚薄一致","type":3,"options":"[\"正确\",\"错误\"]","userAnswer":"[]","answer":"[\"正确\"]","analysis":null,"diffculty":2,"rightOrWrong":2,"score":1.00,"userQuestionScenarios":null},{"examQuestionId":"1571826503674504","examQuestionTitle":"冷制冷吃类菜品都是不经加热处理的，调味后直接装盘上桌，对卫生要求特别高，在操作过程中要严格对餐具、用具进行消毒处理，加工时要戴手套，冷菜间要配备专用的卫生设备。","type":3,"options":"[\"正确\",\"错误\"]","userAnswer":"[]","answer":"[\"正确\"]","analysis":null,"diffculty":3,"rightOrWrong":2,"score":1.00,"userQuestionScenarios":null},{"examQuestionId":"1571826432969148","examQuestionTitle":"切割成形后的原料不须符合所制菜肴在色彩、形状、质感、数量上的要求。","type":3,"options":"[\"正确\",\"错误\"]","userAnswer":"[]","answer":"[\"错误\"]","analysis":null,"diffculty":3,"rightOrWrong":2,"score":1.00,"userQuestionScenarios":null},{"examQuestionId":"1571826505919305","examQuestionTitle":"冻结的原料必须经解冻后才能进行烹饪加工。","type":3,"options":"[\"正确\",\"错误\"]","userAnswer":"[]","answer":"[\"正确\"]","analysis":null,"diffculty":3,"rightOrWrong":2,"score":1.00,"userQuestionScenarios":null},{"examQuestionId":"1571826506138338","examQuestionTitle":"切割成形后的原料不必须符合膳食营养的要求。","type":3,"options":"[\"正确\",\"错误\"]","userAnswer":"[]","answer":"[\"错误\"]","analysis":null,"diffculty":3,"rightOrWrong":2,"score":1.00,"userQuestionScenarios":null},{"examQuestionId":"1571826505441969","examQuestionTitle":"菜肴出勺装盘的要点的拖倒时勺身倾斜，一边拖倒，一边移动，迅速敏捷，干净利落。","type":3,"options":"[\"正确\",\"错误\"]","userAnswer":"[]","answer":"[\"正确\"]","analysis":null,"diffculty":3,"rightOrWrong":2,"score":1.00,"userQuestionScenarios":null},{"examQuestionId":"1571826503485785","examQuestionTitle":"蛋白质在水中加热会发生变性，甚至凝固，由于加热破坏了蛋白的次级键，是蛋白质易被酶水解，容易被人体消化吸收。","type":3,"options":"[\"正确\",\"错误\"]","userAnswer":"[]","answer":"[\"正确\"]","analysis":null,"diffculty":2,"rightOrWrong":2,"score":1.00,"userQuestionScenarios":null},{"examQuestionId":"1571826502102500","examQuestionTitle":"沸水预热法蔬菜原料下锅时水要沸腾，水要多，水面要宽，注意加热约时间要短，绿色蔬菜烫后要迅速入冷水中降温。","type":3,"options":"[\"正确\",\"错误\"]","userAnswer":"[]","answer":"[\"正确\"]","analysis":null,"diffculty":2,"rightOrWrong":2,"score":1.00,"userQuestionScenarios":null},{"examQuestionId":"1571826502613181","examQuestionTitle":"菜肴的组配是确定了菜肴的规格质量，就确定了菜肴的价格、营养成分、烹调方法、口味、造型、色泽等。","type":3,"options":"[\"正确\",\"错误\"]","userAnswer":"[]","answer":"[\"正确\"]","analysis":null,"diffculty":3,"rightOrWrong":2,"score":1.00,"userQuestionScenarios":null},{"examQuestionId":"1571826433417457","examQuestionTitle":"点缀品的大小，色彩应与冷盘的样式相协调与冷盘的规格相符合。","type":3,"options":"[\"正确\",\"错误\"]","userAnswer":"[]","answer":"[\"正确\"]","analysis":null,"diffculty":3,"rightOrWrong":2,"score":1.00,"userQuestionScenarios":null},{"examQuestionId":"1571826431787497","examQuestionTitle":"正斜刀法适用于具有脆性且黏滑的原料，如熟牛肉、猪肚。","type":3,"options":"[\"正确\",\"错误\"]","userAnswer":"[]","answer":"[\"错误\"]","analysis":null,"diffculty":2,"rightOrWrong":2,"score":1.00,"userQuestionScenarios":null},{"examQuestionId":"1571826431570818","examQuestionTitle":"肌纤维密度和肌纤维直径与肉品嫩度及风味有很重要关系，肌纤维越细、密度越大、肉质也越细嫩、风味也越好。","type":3,"options":"[\"正确\",\"错误\"]","userAnswer":"[]","answer":"[\"正确\"]","analysis":null,"diffculty":3,"rightOrWrong":2,"score":1.00,"userQuestionScenarios":null},{"examQuestionId":"1571826506596772","examQuestionTitle":"助翻的操作要求是用左手持手勺推动菜肴，使之全部翻转。","type":3,"options":"[\"正确\",\"错误\"]","userAnswer":"[]","answer":"[\"正确\"]","analysis":null,"diffculty":3,"rightOrWrong":2,"score":1.00,"userQuestionScenarios":null},{"examQuestionId":"1571826432389181","examQuestionTitle":"条与丝形式相近，所以切就相同。","type":3,"options":"[\"正确\",\"错误\"]","userAnswer":"[]","answer":"[\"错误\"]","analysis":null,"diffculty":3,"rightOrWrong":2,"score":1.00,"userQuestionScenarios":null},{"examQuestionId":"1571826504057368","examQuestionTitle":"“宫保鸡丁”“三鲜鸭羹”“双菇鸽松”等名菜，就是通过原料的分割和剔骨整理加工来实现的，优良的风味特征被充分发挥出来。","type":3,"options":"[\"正确\",\"错误\"]","userAnswer":"[]","answer":"[\"正确\"]","analysis":null,"diffculty":2,"rightOrWrong":2,"score":1.00,"userQuestionScenarios":null},{"examQuestionId":"1571826503778151","examQuestionTitle":"菜肴“清蒸武昌鱼”是利用蒸的粉蒸的烹调方法加工而成。","type":3,"options":"[\"正确\",\"错误\"]","userAnswer":"[]","answer":"[\"错误\"]","analysis":null,"diffculty":3,"rightOrWrong":2,"score":1.00,"userQuestionScenarios":null}],"fill":[],"radio":[{"examQuestionId":"1571826424535798","examQuestionTitle":"（     ）运用排剁的方法，但又不将原料断离，仅使之骨折，筋断肉质疏松的方法。","type":1,"options":"[\"切法\",\"剁法\",\"排法\",\"其它刀法\"]","userAnswer":"[]","answer":"[\"排法\"]","analysis":null,"diffculty":3,"rightOrWrong":2,"score":1.00,"userQuestionScenarios":null},{"examQuestionId":"1571826424815303","examQuestionTitle":"（     ）刀平刃向外，紧贴皮层，运用推力向前使皮与肉分开。","type":1,"options":"[\"铲\",\"割\",\"敲\",\"吞刀\"]","userAnswer":"[]","answer":"[\"铲\"]","analysis":null,"diffculty":3,"rightOrWrong":2,"score":1.00,"userQuestionScenarios":null},{"examQuestionId":"1571826424427748","examQuestionTitle":"（     ）将原料嵌进刀刃随刀扬起剁下断离的方法，一些带骨的圆而滑的原料常用此刀法。","type":1,"options":"[\"砧剁\",\"排剁\",\"跟刀剁\",\"拍刀剁\"]","userAnswer":"[]","answer":"[\"跟刀剁\"]","analysis":null,"diffculty":3,"rightOrWrong":2,"score":1.00,"userQuestionScenarios":null},{"examQuestionId":"1571826424916431","examQuestionTitle":"（     ）在整块肉的肉面，有规则切片或切块，且皮仍保持完整的刀法。","type":1,"options":"[\"铲\",\"割\",\"敲\",\"吞刀\"]","userAnswer":"[]","answer":"[\"吞刀\"]","analysis":null,"diffculty":3,"rightOrWrong":2,"score":1.00,"userQuestionScenarios":null},{"examQuestionId":"1571826487133953","examQuestionTitle":"运用直刀法加工的（     ），多用于柱形蔬菜和鱼，在多数情况下，直刀段可再加工成更小料形，其刀法与块相同。","type":1,"options":"[\"直刀段\",\"斜刀段\",\"直刀切\",\"平刀片\"]","userAnswer":"[]","answer":"[\"直刀段\"]","analysis":null,"diffculty":3,"rightOrWrong":2,"score":1.00,"userQuestionScenarios":null},{"examQuestionId":"1571826428555915","examQuestionTitle":"刀法的类型；切，剁，排属于（     ）。","type":1,"options":"[\"直刀法\",\"平刀法\",\"斜刀法\",\"其它刀法\"]","userAnswer":"[]","answer":"[\"直刀法\"]","analysis":null,"diffculty":2,"rightOrWrong":2,"score":1.00,"userQuestionScenarios":null},{"examQuestionId":"1571826426649290","examQuestionTitle":"单一主料的配菜要将（     ）与菜品灵活地组合在一起丰富菜品。","type":1,"options":"[\"着色料\",\"基本味料\",\"拌鲜料\",\"调味料\"]","userAnswer":"[]","answer":"[\"调味料\"]","analysis":null,"diffculty":3,"rightOrWrong":2,"score":1.00,"userQuestionScenarios":null},{"examQuestionId":"1571826422397477","examQuestionTitle":"盐水洗涤此方法适用于对（     ）季节之间上市的新鲜蔬菜的洗涤。","type":1,"options":"[\"春季节\",\"冬季节\",\"夏秋季节\",\"春冬季节\"]","userAnswer":"[]","answer":"[\"夏秋季节\"]","analysis":null,"diffculty":3,"rightOrWrong":2,"score":1.00,"userQuestionScenarios":null},{"examQuestionId":"1571826489541655","examQuestionTitle":"一般适用于整只制作菜品的家禽的（     ），如清炖鸡、花椒鸭等。上席后既看不见刀口，又使家禽显得丰满，较为美观。","type":1,"options":"[\"腹开\",\"背开\",\"肋开\",\"侧开\"]","userAnswer":"[]","answer":"[\"背开\"]","analysis":null,"diffculty":2,"rightOrWrong":2,"score":1.00,"userQuestionScenarios":null},{"examQuestionId":"1571826489806148","examQuestionTitle":"采用天然青砂石料凿成，形状类似粗磨石的（     ），这种磨石颗粒细腻、质地坚实，能将刀磨快而不伤刀刃，应用较广。","type":1,"options":"[\"细磨石\",\"粗磨石\",\"油石\",\"钢磨石\"]","userAnswer":"[]","answer":"[\"细磨石\"]","analysis":null,"diffculty":2,"rightOrWrong":2,"score":1.00,"userQuestionScenarios":null},{"examQuestionId":"1571826427358821","examQuestionTitle":"干煸牛肉丝属于（     ）的烹调方法。","type":1,"options":"[\"煸炒\",\"滑炒\",\"焦炒\",\"熟炒\"]","userAnswer":"[]","answer":"[\"煸炒\"]","analysis":null,"diffculty":3,"rightOrWrong":2,"score":1.00,"userQuestionScenarios":null},{"examQuestionId":"1571826423443698","examQuestionTitle":"磨刀的用具常用的有（     ）种。","type":1,"options":"[\"1\",\"2\",\"3\",\"4\"]","userAnswer":"[]","answer":"[\"3\"]","analysis":null,"diffculty":3,"rightOrWrong":2,"score":1.00,"userQuestionScenarios":null},{"examQuestionId":"1571826486951576","examQuestionTitle":"即反斜批的（     ），右侧角度为钝角(约130°-140°），一般来说此刀法所用的是推力，故又叫“斜推批”。","type":1,"options":"[\"正斜刀法\",\"反斜刀法\",\"平刀法\",\"滚刀法\"]","userAnswer":"[]","answer":"[\"反斜刀法\"]","analysis":null,"diffculty":2,"rightOrWrong":2,"score":1.00,"userQuestionScenarios":null},{"examQuestionId":"1571826422964631","examQuestionTitle":"完全解冻的原料应立即加工，烹饪，因为它在（     ）左右温度条件下，氧气酶和微生物的作用非常迅速，很快使肉色变深，并产生异味。","type":1,"options":"[\"20℃\",\"30℃\",\"40℃\",\"50℃\"]","userAnswer":"[]","answer":"[\"30℃\"]","analysis":null,"diffculty":3,"rightOrWrong":2,"score":1.00,"userQuestionScenarios":null},{"examQuestionId":"1571826487671941","examQuestionTitle":"锅中放油 烧热，将葱姜蒜煸香，放入番茄酱炒透，加水，盐，糖熬煮，最后加入白醋，勾芡后淋人热油搅拌均匀，浇在成熟菜品上是（     ）的调配方法。","type":1,"options":"[\"酸甜味-糖醋味\",\"酸甜味-茄汁味\",\"酸甜味-山楂味\",\"栓甜味-荔枝味\"]","userAnswer":"[]","answer":"[\"酸甜味-茄汁味\"]","analysis":null,"diffculty":2,"rightOrWrong":2,"score":1.00,"userQuestionScenarios":null},{"examQuestionId":"1571826427079410","examQuestionTitle":"下列味型最不宜于制作冻类菜肴的是（     ）。","type":1,"options":"[\"家常味\",\"红油味\",\"咸鲜味\",\"姜汁味\"]","userAnswer":"[]","answer":"[\"家常味\"]","analysis":null,"diffculty":3,"rightOrWrong":2,"score":1.00,"userQuestionScenarios":null},{"examQuestionId":"1571826487982304","examQuestionTitle":"主要用于整只烤制家禽的开膛，用（     ）的方法取内脏，家禽在烤制时就不会漏油水，腹部不收缩变形，成品完整。","type":1,"options":"[\"腹开\",\"背开\",\"肋开\",\"不开\"]","userAnswer":"[]","answer":"[\"肋开\"]","analysis":null,"diffculty":2,"rightOrWrong":2,"score":1.00,"userQuestionScenarios":null},{"examQuestionId":"1571826428487832","examQuestionTitle":"（     ）将原料铺成整齐的瓦楞形，再切成丝，肉类原料宜用此法。","type":1,"options":"[\"卷切式\",\"铺切式\",\"叠切式\",\"直切式\"]","userAnswer":"[]","answer":"[\"铺切式\"]","analysis":null,"diffculty":2,"rightOrWrong":2,"score":1.00,"userQuestionScenarios":null},{"examQuestionId":"1571826424152168","examQuestionTitle":"运用拉力切料，刀刃垂直向下，向后运行，适用于韧性原料的加工刀法是（     ）刀法。","type":1,"options":"[\"直切\",\"推切\",\"拉切\",\"铡切\"]","userAnswer":"[]","answer":"[\"拉切\"]","analysis":null,"diffculty":3,"rightOrWrong":2,"score":1.00,"userQuestionScenarios":null},{"examQuestionId":"1571826425583367","examQuestionTitle":"在调配时要合理掌握（     ）与味精的配比关系，一般谷氨 酸钠的添加量与它的添加量成反比。","type":1,"options":"[\"盐\",\"糖\",\"醋\",\"酱油\"]","userAnswer":"[]","answer":"[\"盐\"]","analysis":null,"diffculty":3,"rightOrWrong":2,"score":1.00,"userQuestionScenarios":null},{"examQuestionId":"1571826487703704","examQuestionTitle":"肉食品熟度的标准（以牛肉为标准），（     ）中心为浅灰褐色，外皮色暗，中心温度80°C。","type":1,"options":"[\"全熟\",\"半熟\",\"中熟\",\"烂\"]","userAnswer":"[]","answer":"[\"全熟\"]","analysis":null,"diffculty":2,"rightOrWrong":2,"score":1.00,"userQuestionScenarios":null},{"examQuestionId":"1571826426438506","examQuestionTitle":"配菜过程中，要根据原料的具体品种，菜肴成品的基本特征选择与其形态大小色彩（     ）的盛装器皿。","type":1,"options":"[\"较准确\",\"相弥补\",\"相映衬\",\"相适宜\"]","userAnswer":"[]","answer":"[\"相适宜\"]","analysis":null,"diffculty":3,"rightOrWrong":2,"score":1.00,"userQuestionScenarios":null},{"examQuestionId":"1571826428445111","examQuestionTitle":"（     ）将原料卷成柱形，再切成丝，适用于对薄而韧的大张厚料的加工，如百叶等。","type":1,"options":"[\"卷切式\",\"铺切式\",\"叠切式\",\"直切式\"]","userAnswer":"[]","answer":"[\"卷切式\"]","analysis":null,"diffculty":2,"rightOrWrong":2,"score":1.00,"userQuestionScenarios":null},{"examQuestionId":"1571826487757820","examQuestionTitle":"红烧味，腐乳味，酒酿味，瓜姜味，冰糖味属于（     ）复合味型。","type":1,"options":"[\"咸鲜味\",\"咸甜味\",\"咸香味\",\"酸甜味\"]","userAnswer":"[]","answer":"[\"咸甜味\"]","analysis":null,"diffculty":2,"rightOrWrong":2,"score":1.00,"userQuestionScenarios":null},{"examQuestionId":"1571826486818318","examQuestionTitle":"刀身略短，刀尖突出，刀板较轻薄，重约700gd的（     ）适于切，削，剔等。","type":1,"options":"[\"大方刀\",\"马头刀\",\"圆头刀\",\"尖头刀\"]","userAnswer":"[]","answer":"[\"马头刀\"]","analysis":null,"diffculty":2,"rightOrWrong":2,"score":1.00,"userQuestionScenarios":null},{"examQuestionId":"1571826426800296","examQuestionTitle":"排是将切好的原料平排式叠排（     ）置于盘中的一种拼盘手法。","type":1,"options":"[\"成形\",\"成花\",\"成图案\",\"成行\"]","userAnswer":"[]","answer":"[\"成形\"]","analysis":null,"diffculty":3,"rightOrWrong":2,"score":1.00,"userQuestionScenarios":null},{"examQuestionId":"1571826422995758","examQuestionTitle":"自然缓慢解冻法是将原料放在（     ）的条件下缓慢解冻。","type":1,"options":"[\"0—3℃\",\"4℃\",\"5℃\",\"10℃\"]","userAnswer":"[]","answer":"[\"0—3℃\"]","analysis":null,"diffculty":3,"rightOrWrong":2,"score":1.00,"userQuestionScenarios":null},{"examQuestionId":"1571826426861465","examQuestionTitle":"拍粉托蛋糊的工艺流程是（     ）。","type":1,"options":"[\"拍粉-腌渍-粘蛋液\",\"腌渍-拍粉-粘蛋液\",\"腌渍-粘蛋液-拍粉\",\"拍粉-粘蛋液\"]","userAnswer":"[]","answer":"[\"腌渍-拍粉-粘蛋液\"]","analysis":null,"diffculty":3,"rightOrWrong":2,"score":1.00,"userQuestionScenarios":null},{"examQuestionId":"1571826423575264","examQuestionTitle":"（     ）刀身与刀石贴紧，推拉研磨适用于磨制刀身平薄的批片刀。","type":1,"options":"[\"平磨\",\"翘磨\",\"直磨\",\"平翘结合磨\"]","userAnswer":"[]","answer":"[\"平磨\"]","analysis":null,"diffculty":3,"rightOrWrong":2,"score":1.00,"userQuestionScenarios":null},{"examQuestionId":"1571826487873955","examQuestionTitle":"操作（     ）的程序是将直接可食的或经过加热的原料改刀后，加上调味品拌匀的一种方法。","type":1,"options":"[\"生炝\",\"熟炒\",\"凉拌\",\"醉\"]","userAnswer":"[]","answer":"[\"凉拌\"]","analysis":null,"diffculty":3,"rightOrWrong":2,"score":1.00,"userQuestionScenarios":null},{"examQuestionId":"1571826427242258","examQuestionTitle":"菜心的焯水处理方法（     ）。","type":1,"options":"[\"冷水预熟法\",\"热水预熟法\",\"蒸\",\"炸\"]","userAnswer":"[]","answer":"[\"热水预熟法\"]","analysis":null,"diffculty":3,"rightOrWrong":2,"score":1.00,"userQuestionScenarios":null},{"examQuestionId":"1571826425605398","examQuestionTitle":"白汁味，红汁味，麻酱味，卤香味，蟹肉味，吓子味属于（     ）复合味型。","type":1,"options":"[\"咸鲜味\",\"咸甜味\",\"咸香味\",\"酸甜味\"]","userAnswer":"[]","answer":"[\"咸鲜味\"]","analysis":null,"diffculty":3,"rightOrWrong":2,"score":1.00,"userQuestionScenarios":null},{"examQuestionId":"1571826486772614","examQuestionTitle":"鸡的分档取料后（     ）宜于加工成丁，丝，片，茸等来烹饪菜肴。","type":1,"options":"[\"鸡翅\",\"鸡腿\",\"鸡脯\",\"鸡爪\"]","userAnswer":"[]","answer":"[\"鸡脯\"]","analysis":null,"diffculty":2,"rightOrWrong":2,"score":1.00,"userQuestionScenarios":null},{"examQuestionId":"1571826486574720","examQuestionTitle":"洗涤后的蔬菜用（     ）发生装置制作的水漂泡10分钟左右，可使90%以上的残存化肥，农药，生物等化学物质脱离蔬菜，使蔬菜安全。","type":1,"options":"[\"氯化钠\",\"臭氧\",\"书打水\",\"糖水\"]","userAnswer":"[]","answer":"[\"臭氧\"]","analysis":null,"diffculty":2,"rightOrWrong":2,"score":1.00,"userQuestionScenarios":null},{"examQuestionId":"1571826488267729","examQuestionTitle":"具有脆性且黏滑的原料适用于（     ），如熟牛肉，猪肚，葱段等的加工。   ","type":1,"options":"[\"正斜刀法\",\"反斜刀法\",\"平刀法\",\"滚刀法\"]","userAnswer":"[]","answer":"[\"反斜刀法\"]","analysis":null,"diffculty":2,"rightOrWrong":2,"score":1.00,"userQuestionScenarios":null},{"examQuestionId":"1571826427927561","examQuestionTitle":"是指将原料放入容器中，加用酒和调料制成的调味腌渍，使活体原料（     ）熟成菜的冷菜技法。","type":1,"options":"[\"凉拌\",\"泡\",\"醉\",\"腌\"]","userAnswer":"[]","answer":"[\"醉\"]","analysis":null,"diffculty":3,"rightOrWrong":2,"score":1.00,"userQuestionScenarios":null},{"examQuestionId":"1571826488236512","examQuestionTitle":"运用向外的拉力，片料时，刀刃由刀尖部进入原料，运用向往的推力，由刀尖向刀腰部移动平推断离，对脆嫩性的原料常用（     ）的方法。如生姜等。","type":1,"options":"[\"平片\",\"拉片\",\"锯片\",\"推片\"]","userAnswer":"[]","answer":"[\"推片\"]","analysis":null,"diffculty":2,"rightOrWrong":2,"score":1.00,"userQuestionScenarios":null},{"examQuestionId":"1571826488015466","examQuestionTitle":"干料放入热水中浸泡而不在继续加热使其慢慢泡发涨大，（     ）法多用于形体小，质地㜛的干料。如银鱼，粉丝等。","type":1,"options":"[\"泡发\",\"煮发\",\"焖发\",\"蒸发\"]","userAnswer":"[]","answer":"[\"泡发\"]","analysis":null,"diffculty":3,"rightOrWrong":2,"score":1.00,"userQuestionScenarios":null},{"examQuestionId":"1571826426022137","examQuestionTitle":"（     ）则是刺激食欲的信号，它由辣椒碱产生，吃辣食可消除体内气滞，血滞等症状。","type":1,"options":"[\"酸味\",\"苦味\",\"辣味\",\"咸味\"]","userAnswer":"[]","answer":"[\"辣味\"]","analysis":null,"diffculty":3,"rightOrWrong":2,"score":1.00,"userQuestionScenarios":null},{"examQuestionId":"1571826423813215","examQuestionTitle":"运用向外的推力，批料时刀刃由刀尖部进入原料运用向外的推力，由刀尖向刀腰部移动平推断高对脆嫰性蔬菜常用（     ）此法，如生姜，白菜等的刀法。","type":1,"options":"[\"平批\",\"推批\",\"拉批\",\"锯批\"]","userAnswer":"[]","answer":"[\"推批\"]","analysis":null,"diffculty":3,"rightOrWrong":2,"score":1.00,"userQuestionScenarios":null}],"multiselect":[{"examQuestionId":"1571826497367650","examQuestionTitle":"跟碟调味法主要适用于加热过程中不便于调味，如（     ）烤等菜肴。","type":2,"options":"[\"炸\",\"涮\",\"煎\",\"蒸\"]","userAnswer":"[]","answer":"[\"炸\",\"涮\",\"煎\",\"蒸\"]","analysis":null,"diffculty":2,"rightOrWrong":2,"score":1.00,"userQuestionScenarios":null},{"examQuestionId":"1571826430661449","examQuestionTitle":"酸甜味包括有（     ）的味型。","type":2,"options":"[\"糖醋味\",\"茄汁味\",\"山楂味\",\"荔枝味\"]","userAnswer":"[]","answer":"[\"糖醋味\",\"茄汁味\",\"山楂味\",\"荔枝味\"]","analysis":null,"diffculty":3,"rightOrWrong":2,"score":1.00,"userQuestionScenarios":null},{"examQuestionId":"1571826430569735","examQuestionTitle":"腌浸调味法（     ）。","type":2,"options":"[\"盐腌法\",\"糖腌法\",\"醋腌法\",\"油腌法\"]","userAnswer":"[]","answer":"[\"盐腌法\",\"糖腌法\",\"醋腌法\"]","analysis":null,"diffculty":3,"rightOrWrong":2,"score":1.00,"userQuestionScenarios":null},{"examQuestionId":"1571826497134405","examQuestionTitle":"原料经加热以后，其原料的特征会发生各种各样的变化，包括（     ）、形态变化等。","type":2,"options":"[\"色泽变化\",\"风味变化\",\"质地变化\",\"成分变化\"]","userAnswer":"[]","answer":"[\"色泽变化\",\"风味变化\",\"质地变化\",\"成分变化\"]","analysis":null,"diffculty":2,"rightOrWrong":2,"score":1.00,"userQuestionScenarios":null},{"examQuestionId":"1571826496029626","examQuestionTitle":"主辅料的比例一般为（     ）等形式。","type":2,"options":"[\"0.375694444444444\",\"0.334722222222222\",\"0.29375\",\"0.252777777777778\"]","userAnswer":"[]","answer":"[\"0.375694444444444\",\"0.334722222222222\",\"0.29375\",\"0.252777777777778\"]","analysis":null,"diffculty":3,"rightOrWrong":2,"score":1.00,"userQuestionScenarios":null},{"examQuestionId":"1571826430000501","examQuestionTitle":"原料切割成形前的站立势（     ）。","type":2,"options":"[\"随意站立\",\"双脚呈八字，脚尖与肩齐，两腿直立，挺胸收腹与案距约5cm\",\"双肩水平，双臂收拢自然放松。\",\"目正视，颈自然微屈垂心垂直。\"]","userAnswer":"[]","answer":"[\"双脚呈八字，脚尖与肩齐，两腿直立，挺胸收腹与案距约5cm\",\"双肩水平，双臂收拢自然放松。\",\"目正视，颈自然微屈垂心垂直。\"]","analysis":null,"diffculty":3,"rightOrWrong":2,"score":1.00,"userQuestionScenarios":null},{"examQuestionId":"1571826498075364","examQuestionTitle":"芝麻汤圆的原料有（     ）。","type":2,"options":"[\"水磨糯米粉\",\"糖\",\"芝麻\",\"油\"]","userAnswer":"[]","answer":"[\"水磨糯米粉\",\"糖\",\"芝麻\",\"油\"]","analysis":null,"diffculty":3,"rightOrWrong":2,"score":1.00,"userQuestionScenarios":null},{"examQuestionId":"1571826497250573","examQuestionTitle":"盛装的餐具以平盘为主适合于（     ）类菜品的餐具选用。","type":2,"options":"[\"爆\",\"炒\",\"炸\",\"煎\"]","userAnswer":"[]","answer":"[\"爆\",\"炒\",\"炸\",\"煎\"]","analysis":null,"diffculty":3,"rightOrWrong":2,"score":1.00,"userQuestionScenarios":null},{"examQuestionId":"1571826429865218","examQuestionTitle":"直刀片加工原则有（     ）。","type":2,"options":"[\"依原料质地而定，易碎者应较厚，有韧性的应较薄。\",\"注意原料的纤维纹理方向较老者宜逆向，较嫰者宜顺向\",\"把原料切小为原则\",\"切面光滑，片形均匀，厚薄一致。\"]","userAnswer":"[]","answer":"[\"依原料质地而定，易碎者应较厚，有韧性的应较薄。\",\"注意原料的纤维纹理方向较老者宜逆向，较嫰者宜顺向\",\"切面光滑，片形均匀，厚薄一致。\"]","analysis":null,"diffculty":3,"rightOrWrong":2,"score":1.00,"userQuestionScenarios":null},{"examQuestionId":"1571826430524754","examQuestionTitle":"在烹调中单一味是（     ）。","type":2,"options":"[\"酸\",\"甜\",\"苦\",\"咸\"]","userAnswer":"[]","answer":"[\"酸\",\"甜\",\"苦\",\"咸\"]","analysis":null,"diffculty":3,"rightOrWrong":2,"score":1.00,"userQuestionScenarios":null},{"examQuestionId":"1571826429278685","examQuestionTitle":"依据刀身与原料的接触角度刀法可分为（     ）。","type":2,"options":"[\"平刀法\",\"斜刀法\",\"直刀法\",\"其它刀法\"]","userAnswer":"[]","answer":"[\"平刀法\",\"斜刀法\",\"直刀法\",\"其它刀法\"]","analysis":null,"diffculty":3,"rightOrWrong":2,"score":1.00,"userQuestionScenarios":null},{"examQuestionId":"1571826495767262","examQuestionTitle":"蔬菜类原料的加工要求是（     ）。","type":2,"options":"[\"按蔬菜的种类和食用部分合理加工\",\"采用符合卫生要求的洗涤方法\",\"科学加工，保持营养\",\"配菜加工\"]","userAnswer":"[]","answer":"[\"按蔬菜的种类和食用部分合理加工\",\"采用符合卫生要求的洗涤方法\",\"科学加工，保持营养\"]","analysis":null,"diffculty":3,"rightOrWrong":2,"score":1.00,"userQuestionScenarios":null},{"examQuestionId":"1571826430953246","examQuestionTitle":"加热的目的和作用（     ）。","type":2,"options":"[\"清除或杀死食物的病菌。\",\"促进食物被人体消化吸收\",\"使菜肴美观\",\"改善菜肴风味\"]","userAnswer":"[]","answer":"[\"清除或杀死食物的病菌。\",\"促进食物被人体消化吸收\",\"改善菜肴风味\"]","analysis":null,"diffculty":3,"rightOrWrong":2,"score":1.00,"userQuestionScenarios":null},{"examQuestionId":"1571826429482272","examQuestionTitle":"其它刀法主要有（     ）。","type":2,"options":"[\"削\",\"剔，刮\",\"拍，撬\",\"剜，挖\"]","userAnswer":"[]","answer":"[\"削\",\"剔，刮\",\"拍，撬\",\"剜，挖\"]","analysis":null,"diffculty":3,"rightOrWrong":2,"score":1.00,"userQuestionScenarios":null},{"examQuestionId":"1571826430751268","examQuestionTitle":"预热处理的目的是（     ）。","type":2,"options":"[\"出去原料中的不良气味\",\"为了增加原料的色彩\",\"缩短正式的加热时间，调整原料间的成熟速度。\",\"为食物的储存作准备，使正式熟处理加工更快捷。\"]","userAnswer":"[]","answer":"[\"出去原料中的不良气味\",\"为了增加原料的色彩\",\"缩短正式的加热时间，调整原料间的成熟速度。\",\"为食物的储存作准备，使正式熟处理加工更快捷。\"]","analysis":null,"diffculty":3,"rightOrWrong":2,"score":1.00,"userQuestionScenarios":null},{"examQuestionId":"1571826497503798","examQuestionTitle":"按照刀具的用途来划分，可分为（     ）等。","type":2,"options":"[\"片刀\",\"切刀\",\"斩刀\",\"前片后斩刀\"]","userAnswer":"[]","answer":"[\"片刀\",\"切刀\",\"斩刀\",\"前片后斩刀\"]","analysis":null,"diffculty":3,"rightOrWrong":2,"score":1.00,"userQuestionScenarios":null},{"examQuestionId":"1571826496745761","examQuestionTitle":"刀法中的斜刀法分为（     ）。","type":2,"options":"[\"正斜刀法\",\"反斜刀法\",\"直斜刀法\",\"滚斜刀法\"]","userAnswer":"[]","answer":"[\"正斜刀法\",\"反斜刀法\"]","analysis":null,"diffculty":2,"rightOrWrong":2,"score":1.00,"userQuestionScenarios":null},{"examQuestionId":"1571826430038740","examQuestionTitle":"对整块（只）禽内原料的加工，应遵循分割于整形之中原则，合理运用（     ）和（     ），以适合咀嚼，筷夹食用为度。","type":2,"options":"[\"平刀法\",\"排刀法\",\"反斜刀法\",\"吞刀法\"]","userAnswer":"[]","answer":"[\"排刀法\",\"吞刀法\"]","analysis":null,"diffculty":3,"rightOrWrong":2,"score":1.00,"userQuestionScenarios":null},{"examQuestionId":"1571826497454445","examQuestionTitle":"腌腊制品火腿初加工分（     ）四步完成。","type":2,"options":"[\"浸泡6小时\",\"用热的食用碱水将火腿外表刷干净\",\"加绍兴酒、葱、姜蒸3小时\",\"熟后分割成块\"]","userAnswer":"[]","answer":"[\"浸泡6小时\",\"用热的食用碱水将火腿外表刷干净\",\"加绍兴酒、葱、姜蒸3小时\",\"熟后分割成块\"]","analysis":null,"diffculty":2,"rightOrWrong":2,"score":1.00,"userQuestionScenarios":null},{"examQuestionId":"1571826496622971","examQuestionTitle":"禽类鹌鹑的宰杀方法（     ）。","type":2,"options":"[\"浸水淹死\",\"用酒灌醉\",\"闷死\",\"摔死\"]","userAnswer":"[]","answer":"[\"闷死\",\"摔死\"]","analysis":null,"diffculty":2,"rightOrWrong":2,"score":1.00,"userQuestionScenarios":null}],"qa":[],"sc":[]},"passScore":60.0,"isDisplay":1}}